code_xray/__main__.py
code_xray/tree.py
code_xray/viewer.py
code_xray-2.0.1.dist-info/METADATA
code_xray-2.0.1.dist-info/WHEEL
code_xray-2.0.1.dist-info/entry_points.txt
code_xray-2.0.1.dist-info/top_level.txt
code_xray-2.0.1.dist-info/RECORD
