Metadata-Version: 2.4
Name: code-xray
Version: 2.0.1
Summary: Terminal-based code explainer powered by Ollama
Author-email: Aayush Rajesh Jadhav <aayushrj22@gmail.com>
License: MIT
Requires-Python: >=3.9
Requires-Dist: textual
Requires-Dist: rich
Requires-Dist: httpx
Requires-Dist: typer[all]
Requires-Dist: prompt_toolkit
